norn_dh/__init__.py
norn_dh/alto_tools.py
norn_dh/config.py
norn_dh/corpus_tools.py
norn_dh/imag_corpus.py
norn_dh/mongodb_tools.py
norn_dh/poems.py
norn_dh/public_domain.py
norn_dh/py.typed
norn_dh/text/__init__.py
norn_dh/text/collocation.py
norn_dh/text/concordance.py
norn_dh/text/counting.py
norn_dh/text/dtm.py
norn_dh/utils.py
norn_dh-0.2.0.dist-info/METADATA
norn_dh-0.2.0.dist-info/WHEEL
norn_dh-0.2.0.dist-info/RECORD
