Metadata-Version: 2.1
Name: norn_dh
Version: 0.2.0
Summary: 
License: MIT
Author: Lars Magne Tungland
Author-email: larsmtungland@gmail.com
Requires-Python: >=3.10,<3.13
Classifier: License :: OSI Approved :: MIT License
Classifier: Programming Language :: Python :: 3
Classifier: Programming Language :: Python :: 3.10
Classifier: Programming Language :: Python :: 3.11
Classifier: Programming Language :: Python :: 3.12
Requires-Dist: beautifulsoup4 (>=4.12.2,<5.0.0)
Requires-Dist: dhlab (>=2.26.5,<3.0.0)
Requires-Dist: flask (>=3.0.0,<4.0.0)
Requires-Dist: lxml (>=4.9.3,<5.0.0)
Requires-Dist: openpyxl (>=3.1.2,<4.0.0)
Requires-Dist: pandas (>=2.1.2,<3.0.0)
Requires-Dist: pymongo (>=4.6.1,<5.0.0)
Requires-Dist: python-dotenv (>=1.0.1,<2.0.0)
Requires-Dist: requests (>=2.31.0,<3.0.0)
Requires-Dist: scikit-learn (>=1.3.2,<2.0.0)
Requires-Dist: scipy (>=1.11.4,<2.0.0)
Requires-Dist: tqdm (>=4.66.1,<5.0.0)
